Level-2/Level-2.B/gcd/gcd.v
module gcd(a,b,gcd);
parameter w=8;
input [w-1:0] a,b;
output reg [w-1:0] gcd;
reg [w-1:0] ain,bin;

always @(a or b)
begin
ain=a;bin=b;
while(ain != bin)
begin
if(ain<bin)
bin=bin-ain;
else 
ain=ain-bin;
end
gcd=ain;
end
endmodule

Level-2/Level-2.B/gcd/gcd_tb.v
module gcd_tb();
parameter w=8;
reg [w-1:0] a,b;
wire [w-1:0] gcd;

gcd DUT(.a(a),.b(b),.gcd(gcd));
initial begin
$dumpfile("gcd_test.vcd");
$dumpvars(0,gcd_tb);

a=20;b=80;
#5 a=80;b=45;
#5 a=84;b=44;
#5 a=2;b=7;
#5 a=180;b=160;
#5 a=90;b=45;
#5 a=83;b=4;
#5 a=13;b=7;
#5 $finish;
end
endmodule

Level-2/Level-2.B/gcd/gcd_test.vcd
$date
	Sun Jul  2 19:29:34 2023
$end
$version
	Icarus Verilog
$end
$timescale
	1s
$end
$scope module gcd_tb $end
$var wire 8 ! gcd [7:0] $end
$var reg 8 " a [7:0] $end
$var reg 8 # b [7:0] $end
$scope module DUT $end
$var wire 8 $ a [7:0] $end
$var wire 8 % b [7:0] $end
$var reg 8 & ain [7:0] $end
$var reg 8 ' bin [7:0] $end
$var reg 8 ( gcd [7:0] $end
$upscope $end
$upscope $end
$enddefinitions $end
#0
$dumpvars
b10100 (
b10100 '
b10100 &
b1010000 %
b10100 $
b1010000 #
b10100 "
b10100 !
$end
#5
b101 !
b101 (
b101 '
b101 &
b101101 #
b101101 %
b1010000 "
b1010000 $
#10
b100 !
b100 (
b100 '
b100 &
b101100 #
b101100 %
b1010100 "
b1010100 $
#15
b1 !
b1 (
b1 '
b1 &
b111 #
b111 %
b10 "
b10 $
#20
b10100 !
b10100 (
b10100 '
b10100 &
b10100000 #
b10100000 %
b10110100 "
b10110100 $
#25
b101101 !
b101101 (
b101101 '
b101101 &
b101101 #
b101101 %
b1011010 "
b1011010 $
#30
b1 !
b1 (
b1 '
b1 &
b100 #
b100 %
b1010011 "
b1010011 $
#35
b1 '
b1 &
b111 #
b111 %
b1101 "
b1101 $
