Level-2/Level-2.B/minority_detector/min_det.v
module min_det(a,b,c,f);
input a,b,c;
output f;
assign f=~((a&b)|(a&c)|(b&c));
endmodule

Level-2/Level-2.B/minority_detector/min_det_tb.v
module min_det_tb();
reg a,b,c;
wire f;

min_det DUT(.a(a),.b(b),.c(c),.f(f));
initial begin
$dumpfile("min_det_test.vcd");
$dumpvars(0,min_det_tb);
   a=0;b=0;c=0;
#5 a=0;b=0;c=1;
#5 a=0;b=1;c=0;
#5 a=0;b=1;c=1;
#5 a=1;b=0;c=0;
#5 a=1;b=0;c=1;
#5 a=1;b=1;c=0;
#5 a=1;b=1;c=1;
#5 $finish;
end
endmodule

Level-2/Level-2.B/minority_detector/min_det_test.vcd
$date
	Mon Jul  3 12:00:20 2023
$end
$version
	Icarus Verilog
$end
$timescale
	1s
$end
$scope module min_det_tb $end
$var wire 1 ! f $end
$var reg 1 " a $end
$var reg 1 # b $end
$var reg 1 $ c $end
$scope module DUT $end
$var wire 1 " a $end
$var wire 1 # b $end
$var wire 1 $ c $end
$var wire 1 ! f $end
$upscope $end
$upscope $end
$enddefinitions $end
#0
$dumpvars
0$
0#
0"
1!
$end
#5
1$
#10
0$
1#
#15
0!
1$
#20
1!
0$
0#
1"
#25
0!
1$
#30
0$
1#
#35
1$
