Level-2/Level-2.A/T_ff/tff.v
module tff(clk,T,q,q_bar);
input clk,T;
output reg q=0;
output q_bar;
always @(posedge clk)
begin
if(T)
q<=~q;
else
q<=q;
end 
assign q_bar=~q;

endmodule

Level-2/Level-2.A/T_ff/tff_tb.v
module tff_tb();
reg clk,T;
wire q,q_bar;

tff DUT(.clk(clk),.T(T),.q(q),.q_bar(q_bar));
always begin
#5 clk=~ clk;
end

initial begin
$dumpfile("tff_test.vcd");
$dumpvars(0,tff_tb);
clk=0;
T=0;
#5 T=1;
#5 T=0;
#5 T=1;
#5 T=1;
#5 T=0;
#5 T=0;
#5 T=1;
#5 T=1;
#5 T=0;
#5 T=0;
#5 T=0;
#5 T=0;
#5 T=1;

#5 $finish;
end
endmodule

Level-2/Level-2.A/T_ff/tff_test.vcd
$date
	Tue Jul  4 11:32:21 2023
$end
$version
	Icarus Verilog
$end
$timescale
	1s
$end
$scope module tff_tb $end
$var wire 1 ! q_bar $end
$var wire 1 " q $end
$var reg 1 # T $end
$var reg 1 $ clk $end
$scope module DUT $end
$var wire 1 # T $end
$var wire 1 $ clk $end
$var wire 1 ! q_bar $end
$var reg 1 " q $end
$upscope $end
$upscope $end
$enddefinitions $end
#0
$dumpvars
0$
0#
0"
1!
$end
#5
0!
1"
1#
1$
#10
0#
0$
#15
1!
0"
1#
1$
#20
0$
#25
0#
1$
#30
0$
#35
0!
1"
1#
1$
#40
0$
#45
0#
1$
#50
0$
#55
1$
#60
0$
#65
1!
0"
1#
1$
