Level-2/Level-2.B/synchronous counter/sync_cntr.v
module sync_cntr(clk,rst,up_down,count);
input clk,rst,up_down;
output [3:0] count;
reg [3:0] count=0;
always @(posedge clk)
begin
if(rst == 1)
count <= 0;
else 
if (up_down==1)
count <= count +1;
else
count <= count -1;
end
endmodule

Level-2/Level-2.B/synchronous counter/sync_cntr_tb.v
module sync_cntr_tb();

reg clk,rst,up_down;
wire [3:0] count;

sync_cntr DUT(.clk(clk),.rst(rst),.up_down(up_down),.count(count));
always begin
#5 clk=~clk;
end
initial begin
$dumpfile("sync_test.vcd");
$dumpvars(0,sync_cntr_tb);
 clk=0; rst=0;
#5 up_down =1;
#5 up_down =1;
#5 up_down =1;
#5 up_down =1;
#5 up_down =0;
#5 up_down =0;
#5 up_down =0;
#5 up_down =0;
#2 rst=1;
#3 rst=0;
#5 up_down =0;
#5 up_down =0;
#5 up_down =0;
#5 up_down =0;
#5 up_down =0;
#5 up_down =0;
#5 up_down =0;
#5 up_down =0;
#5 $finish;
end
endmodule

Level-2/Level-2.B/synchronous counter/sync_test.vcd
$date
	Tue Jul  4 11:10:42 2023
$end
$version
	Icarus Verilog
$end
$timescale
	1s
$end
$scope module sync_cntr_tb $end
$var wire 4 ! count [3:0] $end
$var reg 1 " clk $end
$var reg 1 # rst $end
$var reg 1 $ up_down $end
$scope module DUT $end
$var wire 1 " clk $end
$var wire 1 # rst $end
$var wire 1 $ up_down $end
$var reg 4 % count [3:0] $end
$upscope $end
$upscope $end
$enddefinitions $end
#0
$dumpvars
b0 %
x$
0#
0"
b0 !
$end
#5
b1 !
b1 %
1$
1"
#10
0"
#15
b10 !
b10 %
1"
#20
0"
#25
b1 !
b1 %
0$
1"
#30
0"
#35
b0 !
b0 %
1"
#40
0"
#42
1#
#45
b1111 !
b1111 %
0#
1"
#50
0"
#55
b1110 !
b1110 %
1"
#60
0"
#65
b1101 !
b1101 %
1"
#70
0"
#75
b1100 !
b1100 %
1"
#80
0"
#85
b1011 !
b1011 %
1"
