Level-2/Level-2.A/mux16to1/mux16to1.v
module mux16to1(W,S,Y);
input [0:15]W;
input [3:0]S;
output reg Y;

always @(S or W)
case(S)
0:Y=W[0];
1:Y=W[1];
2:Y=W[2];
3:Y=W[3];
4:Y=W[4];
5:Y=W[5];
6:Y=W[6];
7:Y=W[7];
8:Y=W[8];
9:Y=W[9];
10:Y=W[10];
11:Y=W[11];
12:Y=W[12];
13:Y=W[13];
14:Y=W[14];
15:Y=W[15];
default:Y=0;
endcase
endmodule

Level-2/Level-2.A/mux16to1/mux16to1_tb.v
module mux16to1_tb();
reg [0:15]W;
reg [3:0]S;
wire Y;
mux16to1 DUT(.S(S),.W(W),.Y(Y));
always begin
$dumpfile("mux16to1_test.vcd");
$dumpvars(0,mux16to1_tb);
    W=43690;S=0;
#10 W=43690;S=1;
#10 W=43690;S=2;
#10 W=43690;S=3;
#10 W=43690;S=4;
#10 W=43690;S=5;
#10 W=43690;S=6;
#10 W=43690;S=7;
#10 W=43690;S=8;
#10 W=43690;S=9;
#10 W=43690;S=10;
#10 W=43690;S=11;
#10 W=43690;S=12;
#10 W=43690;S=13;
#10 W=43690;S=14;
#10 W=43690;S=15;
#10 $finish;
end
endmodule

Level-2/Level-2.A/mux16to1/mux16to1_test.vcd
$date
	Fri Jun 30 15:37:10 2023
$end
$version
	Icarus Verilog
$end
$timescale
	1s
$end
$scope module mux16to1_tb $end
$var wire 1 ! Y $end
$var reg 4 " S [3:0] $end
$var reg 16 # W [0:15] $end
$scope module DUT $end
$var wire 4 $ S [3:0] $end
$var wire 16 % W [0:15] $end
$var reg 1 ! Y $end
$upscope $end
$upscope $end
$enddefinitions $end
#0
$dumpvars
b1010101010101010 %
b0 $
b1010101010101010 #
b0 "
1!
$end
#10
0!
b1 "
b1 $
#20
1!
b10 "
b10 $
#30
0!
b11 "
b11 $
#40
1!
b100 "
b100 $
#50
0!
b101 "
b101 $
#60
1!
b110 "
b110 $
#70
0!
b111 "
b111 $
#80
1!
b1000 "
b1000 $
#90
0!
b1001 "
b1001 $
#100
1!
b1010 "
b1010 $
#110
0!
b1011 "
b1011 $
#120
1!
b1100 "
b1100 $
#130
0!
b1101 "
b1101 $
#140
1!
b1110 "
b1110 $
#150
0!
b1111 "
b1111 $
