Level-2/Level-2.A/DFF/dff.v
module dff(D,clk,Q);
input D,clk;
output reg Q ;
always @(posedge clk)
Q=D;
endmodule

Level-2/Level-2.A/DFF/dff_tb.v
module dff_tb();
reg D,clk;
wire Q;

dff DUT(.D(D),.clk(clk),.Q(Q));
always begin 
#5 clk=~clk;
end
initial begin
$dumpfile("dff_test.vcd");
$dumpvars(0,dff_tb);
clk=0;

 D=1;
#2 D=0;
#7 D=1;
#1 D=0;
#2 D=1;
#7 D=1;
#1 D=0;
#2 D=0;
#7 D=1;
#1 D=0;
#2 D=1;
#7 D=1;
#1 D=0;
#5 $finish;
end
endmodule

Level-2/Level-2.A/DFF/dff_test.vcd
$date
	Sat Jul  1 14:17:13 2023
$end
$version
	Icarus Verilog
$end
$timescale
	1s
$end
$scope module dff_tb $end
$var wire 1 ! Q $end
$var reg 1 " D $end
$var reg 1 # clk $end
$scope module DUT $end
$var wire 1 " D $end
$var wire 1 # clk $end
$var reg 1 ! Q $end
$upscope $end
$upscope $end
$enddefinitions $end
#0
$dumpvars
0#
1"
x!
$end
#2
0"
#5
0!
1#
#9
1"
#10
0"
0#
#12
1"
#15
1!
1#
#20
0"
0#
#25
0!
1#
#29
1"
#30
0"
0#
#32
1"
#35
1!
1#
#40
0"
0#
#45
0!
1#
