Level-2/Level-2.A/seg7/seg7.v
module seg7(bcd,leds);
input [3:0]bcd;
output reg [1:7]leds;
always@(bcd)
 case(bcd)  //abcdefg assuming to be common cathode seven segment display
0: leds=7'b1111110;
1: leds=7'b0110000;
2: leds=7'b1101101;
3: leds=7'b1111001;
4: leds=7'b0110011;
5: leds=7'b1011011;
6: leds=7'b1011111;
7: leds=7'b1110000;
8: leds=7'b1111111;
9: leds=7'b1111011;
default :leds=7'bx;
endcase
endmodule

Level-2/Level-2.A/seg7/seg7_tb.v
module seg7_tb();
reg [3:0]bcd;
wire [1:7] leds;

seg7 DUT(.bcd(bcd),.leds(leds));
initial begin
$dumpfile("seg7_test.vcd");
$dumpvars(0,seg7_tb);
bcd=0;
#5 bcd=1;
#5 bcd=2;
#5 bcd=3;
#5 bcd=4;
#5 bcd=5;
#5 bcd=6;
#5 bcd=7;
#5 bcd=8;
#5 bcd=9;
#5 $finish;
end
endmodule

Level-2/Level-2.A/seg7/seg7_test.vcd
$date
	Sat Jul  1 10:44:47 2023
$end
$version
	Icarus Verilog
$end
$timescale
	1s
$end
$scope module seg7_tb $end
$var wire 7 ! leds [1:7] $end
$var reg 4 " bcd [3:0] $end
$scope module DUT $end
$var wire 4 # bcd [3:0] $end
$var reg 7 $ leds [1:7] $end
$upscope $end
$upscope $end
$enddefinitions $end
#0
$dumpvars
b1111110 $
b0 #
b0 "
b1111110 !
$end
#5
b110000 !
b110000 $
b1 "
b1 #
#10
b1101101 !
b1101101 $
b10 "
b10 #
#15
b1111001 !
b1111001 $
b11 "
b11 #
#20
b110011 !
b110011 $
b100 "
b100 #
#25
b1011011 !
b1011011 $
b101 "
b101 #
#30
b1011111 !
b1011111 $
b110 "
b110 #
#35
b1110000 !
b1110000 $
b111 "
b111 #
#40
b1111111 !
b1111111 $
b1000 "
b1000 #
#45
b1111011 !
b1111011 $
b1001 "
b1001 #
