Level-2/Level-2.B/bidirectional_shift_register/BSR.v
module BSR(d,dir,clk,rst,en,out);
parameter MSB=4;
input d,dir,clk,en,rst;
output reg [MSB-1:0]out;

always @(posedge clk or en or rst or d or dir)
if(!rst)
  out<=0;
else begin
if(en)
  case(dir)
  0:out <= {out[MSB-2:0],d}; //left
  1:out <= {d,out[MSB-1:1]}; //right
  endcase
else
 out <=out;
end
endmodule

Level-2/Level-2.B/bidirectional_shift_register/BSR_tb.v
module BSR_tb();
parameter MSB=4;
reg d,clk,dir,en,rst;
wire [MSB-1:0]out;

BSR DUT(.d(d),.clk(clk),.dir(dir),.en(en),.rst(rst),.out(out));
always begin
#5 clk=~clk;
end
initial begin
$dumpfile("BSR_test.vcd");
$dumpvars(0,BSR_tb);
clk=0;rst=0;

d=1;dir=0;en=1;rst=0;
#5 d=1;dir=0;en=1;rst=1;
#5 d=1;dir=1;en=1;rst=1;
#5 d=1;dir=0;en=0;rst=1;
#5 d=1;dir=0;en=1;rst=0;
#5 d=0;dir=1;en=1;rst=1;
#5 d=0;dir=1;en=0;rst=1;
#5 d=0;dir=0;en=1;rst=1;
 #5 $finish;
end 
endmodule

Level-2/Level-2.B/bidirectional_shift_register/BSR_test.vcd
$date
	Mon Jul  3 11:28:29 2023
$end
$version
	Icarus Verilog
$end
$timescale
	1s
$end
$scope module BSR_tb $end
$var wire 4 ! out [3:0] $end
$var reg 1 " clk $end
$var reg 1 # d $end
$var reg 1 $ dir $end
$var reg 1 % en $end
$var reg 1 & rst $end
$scope module DUT $end
$var wire 1 " clk $end
$var wire 1 # d $end
$var wire 1 $ dir $end
$var wire 1 % en $end
$var wire 1 & rst $end
$var reg 4 ' out [3:0] $end
$upscope $end
$upscope $end
$enddefinitions $end
#0
$dumpvars
b0 '
0&
1%
0$
1#
0"
b0 !
$end
#5
b1 !
b1 '
1&
1"
#10
b1000 !
b1000 '
1$
0"
#15
0%
0$
1"
#20
b0 !
b0 '
0&
1%
0"
#25
1&
1$
0#
1"
#30
0%
0"
#35
1%
0$
1"
