Level-2/Level-2.B/ALU/ALU.v
module ALU(s,A,B,F); //74381 ALU
input [2:0]s;
input [3:0]A,B;
output reg [3:0]F;
always @(s or A or B)
case(s)
0:F=0;
1:F=B-A;
2:F=A-B;
3:F=A+B;
4:F=A^B;
5:F=A|B;
6:F=A&B;
7:F=15;
endcase
endmodule

Level-2/Level-2.B/ALU/ALU_tb.v
module ALU_tb();
reg [3:0]A,B;
reg [2:0]s;
wire [3:0]F;

ALU DUT(.A(A),.B(B),.s(s),.F(F));

initial begin
$dumpfile("ALU_test.vcd");
$dumpvars(0,ALU_tb);
s=0;A=5;B=10;
#5 s=1;A=5;B=10;
#5 s=2;A=5;B=10;
#5 s=3;A=5;B=10;
#5 s=4;A=5;B=10;
#5 s=5;A=5;B=10;
#5 s=6;A=5;B=10;
#5 s=7;A=5;B=10;
#5 $finish;
end 
endmodule

Level-2/Level-2.B/ALU/ALU_test.vcd
$date
	Sat Jul  1 12:08:36 2023
$end
$version
	Icarus Verilog
$end
$timescale
	1s
$end
$scope module ALU_tb $end
$var wire 4 ! F [3:0] $end
$var reg 4 " A [3:0] $end
$var reg 4 # B [3:0] $end
$var reg 3 $ s [2:0] $end
$scope module DUT $end
$var wire 4 % A [3:0] $end
$var wire 4 & B [3:0] $end
$var wire 3 ' s [2:0] $end
$var reg 4 ( F [3:0] $end
$upscope $end
$upscope $end
$enddefinitions $end
#0
$dumpvars
b0 (
b0 '
b1010 &
b101 %
b0 $
b1010 #
b101 "
b0 !
$end
#5
b101 !
b101 (
b1 $
b1 '
#10
b1011 !
b1011 (
b10 $
b10 '
#15
b1111 !
b1111 (
b11 $
b11 '
#20
b100 $
b100 '
#25
b101 $
b101 '
#30
b0 !
b0 (
b110 $
b110 '
#35
b1111 !
b1111 (
b111 $
b111 '
