Level-2/Level-2.A/mux2to1/mux2to1.v
module mux2to1(a,b,s,Y);
input a,b,s;
output reg Y;
 always@(s,a,b)
 begin
	 if(s)
		 Y=b;
	 else 
		 Y=a;
 end
 endmodule

Level-2/Level-2.A/mux2to1/mux2to1_tb.v
module mux2to1_tb();
 reg at,bt,st;
 wire Yt;

 mux2to1 u0_DUT(.a(at),.b(bt),.s(st),.Y(Yt));
initial begin
$dumpfile("mux2to1_test.vcd");
$dumpvars(0,mux2to1_tb);
	     st=0;at=0;bt=0;
	 #10 st=0;at=0;bt=1;
	 #10 st=0;at=1;bt=0;
	 #10 st=0;at=1;bt=1;
	 #10 st=1;at=0;bt=0;
	 #10 st=1;at=0;bt=1;
	 #10 st=1;at=1;bt=0;
	 #10 st=1;at=1;bt=1;
#10 $finish;
 end
 endmodule

Level-2/Level-2.A/mux2to1/mux2to1_test.vcd
$date
	Fri Jun 30 14:35:28 2023
$end
$version
	Icarus Verilog
$end
$timescale
	1s
$end
$scope module mux2to1_tb $end
$var wire 1 ! Yt $end
$var reg 1 " at $end
$var reg 1 # bt $end
$var reg 1 $ st $end
$scope module u0_DUT $end
$var wire 1 " a $end
$var wire 1 # b $end
$var wire 1 $ s $end
$var reg 1 ! Y $end
$upscope $end
$upscope $end
$enddefinitions $end
#0
$dumpvars
0$
0#
0"
0!
$end
#10
1#
#20
1!
0#
1"
#30
1#
#40
0!
0#
0"
1$
#50
1!
1#
#60
0!
0#
1"
#70
1!
1#
