Level-2/Level-2.A/fulladder/fulladder.v
module fulladder(a,b,cin,sum,cout);
input a,b,cin;
output sum,cout;
assign sum=a^b^cin;
assign cout=(a & b)|(b & cin)|(a & cin);
endmodule

Level-2/Level-2.A/fulladder/fulladder_tb.v
module fulladder_tb();
reg a,b,cin;
wire sum,cout;
fulladder u0_DUT(.a(a),.b(b),.cin(cin),.sum(sum),.cout(cout));
initial begin
$dumpfile("fullader_test.vcd");
$dumpvars(0,fulladder_tb);   
 a=0;b=0;cin=0;
#10 a=0;b=0;cin=1;
#10 a=0;b=1;cin=0;
#10 a=0;b=1;cin=1;
#10 a=1;b=0;cin=0;
#10 a=1;b=0;cin=1;
#10 a=1;b=1;cin=0;
#10 a=1;b=1;cin=1;
#10 $finish;
end
endmodule

Level-2/Level-2.A/fulladder/fullader_test.vcd
$date
	Fri Jun 30 14:08:15 2023
$end
$version
	Icarus Verilog
$end
$timescale
	1s
$end
$scope module fulladder_tb $end
$var wire 1 ! sum $end
$var wire 1 " cout $end
$var reg 1 # a $end
$var reg 1 $ b $end
$var reg 1 % cin $end
$scope module u0_DUT $end
$var wire 1 # a $end
$var wire 1 $ b $end
$var wire 1 % cin $end
$var wire 1 " cout $end
$var wire 1 ! sum $end
$upscope $end
$upscope $end
$enddefinitions $end
#0
$dumpvars
0%
0$
0#
0"
0!
$end
#10
1!
1%
#20
0%
1$
#30
1"
0!
1%
#40
0"
1!
0%
0$
1#
#50
1"
0!
1%
#60
0%
1$
#70
1!
1%
